MANIFEST.in
README.rst
cggwave.pxd
ggwave.bycython.cpp
ggwave.pyx
setup.py
ggwave.egg-info/PKG-INFO
ggwave.egg-info/SOURCES.txt
ggwave.egg-info/dependency_links.txt
ggwave.egg-info/top_level.txt
ggwave/include/ggwave/ggwave.h
ggwave/src/CMakeLists.txt
ggwave/src/ggwave.cpp
ggwave/src/resampler.cpp
ggwave/src/resampler.h
ggwave/src/reed-solomon/LICENSE
ggwave/src/reed-solomon/gf.hpp
ggwave/src/reed-solomon/poly.hpp
ggwave/src/reed-solomon/rs.hpp