Metadata-Version: 1.0
Name: ggwave
Version: 0.3.0
Summary: Tiny data-over-sound library.
Home-page: https://github.com/ggerganov/ggwave
Author: Georgi Gerganov
Author-email: ggerganov@gmail.com
License: MIT
Keywords: data-over-sound fsk ecc serverless pairing qrcode ultrasound
Platform: UNKNOWN
